fourthdimension/__init__.py
fourthdimension/fd_core/__init__.py
fourthdimension/fd_core/fd_client.py
fourthdimension/fd_core/fd_httpclient.py
fourthdimension/fd_core/fd_utils.py
fourthdimension/fd_core/chat/__init__.py
fourthdimension/fd_core/chat/__version__.py
fourthdimension/fd_core/chat/_client.py
fourthdimension/fd_core/chat/api_resource/__init__.py
fourthdimension/fd_core/chat/api_resource/batches.py
fourthdimension/fd_core/chat/api_resource/embeddings.py
fourthdimension/fd_core/chat/api_resource/files.py
fourthdimension/fd_core/chat/api_resource/images.py
fourthdimension/fd_core/chat/api_resource/chat/__init__.py
fourthdimension/fd_core/chat/api_resource/chat/async_completions.py
fourthdimension/fd_core/chat/api_resource/chat/chat.py
fourthdimension/fd_core/chat/api_resource/chat/completions.py
fourthdimension/fd_core/chat/core/__init__.py
fourthdimension/fd_core/chat/core/_base_api.py
fourthdimension/fd_core/chat/core/_base_compat.py
fourthdimension/fd_core/chat/core/_base_models.py
fourthdimension/fd_core/chat/core/_base_type.py
fourthdimension/fd_core/chat/core/_constants.py
fourthdimension/fd_core/chat/core/_errors.py
fourthdimension/fd_core/chat/core/_files.py
fourthdimension/fd_core/chat/core/_http_client.py
fourthdimension/fd_core/chat/core/_jwt_token.py
fourthdimension/fd_core/chat/core/_legacy_binary_response.py
fourthdimension/fd_core/chat/core/_legacy_response.py
fourthdimension/fd_core/chat/core/_legacy_xlsx_response.py
fourthdimension/fd_core/chat/core/_request_opt.py
fourthdimension/fd_core/chat/core/_response.py
fourthdimension/fd_core/chat/core/_sse_client.py
fourthdimension/fd_core/chat/core/logs.py
fourthdimension/fd_core/chat/core/pagination.py
fourthdimension/fd_core/chat/core/_utils/__init__.py
fourthdimension/fd_core/chat/core/_utils/_transform.py
fourthdimension/fd_core/chat/core/_utils/_typing.py
fourthdimension/fd_core/chat/core/_utils/_utils.py
fourthdimension/fd_core/chat/types/__init__.py
fourthdimension-2.0.8.dist-info/METADATA
fourthdimension-2.0.8.dist-info/WHEEL
fourthdimension-2.0.8.dist-info/top_level.txt
fourthdimension-2.0.8.dist-info/RECORD
