Metadata-Version: 2.1
Name: fourthdimension
Version: 2.0.8
Summary: fourthdimension
Home-page: https://gitee.com/hustai/FourthDimension
Author: ytkj
Author-email: lijinxin@yantu-ai.com
Classifier: Programming Language :: Python :: 3
Classifier: License :: OSI Approved :: Apache Software License
Classifier: Operating System :: OS Independent
Requires-Python: >=3.9
Requires-Dist: httpx ==0.27.0
Requires-Dist: pydantic
Requires-Dist: pandas
Requires-Dist: pyjwt
Requires-Dist: pydantic-core
Requires-Dist: cachetools
Requires-Dist: networkx
Requires-Dist: termcolor
